languagepy/__init__.py
languagepy/command_line.py
languagepy/exemplu.py
languagepy/exemplu.ro.py
languagepy/source.py
languagepy-0.1.dist-info/DESCRIPTION.rst
languagepy-0.1.dist-info/METADATA
languagepy-0.1.dist-info/RECORD
languagepy-0.1.dist-info/WHEEL
languagepy-0.1.dist-info/entry_points.txt
languagepy-0.1.dist-info/metadata.json
languagepy-0.1.dist-info/top_level.txt
