Metadata-Version: 2.0
Name: languagepy
Version: 0.1
Summary: Write Python in your native language and transpile it to standard Python
Home-page: https://languagepy.org
Author: Jan Cavel
Author-email: mail@caveljan.com
License: MIT
Project-URL: Website, https://languagepy.org
Project-URL: Documentation, https://docs.languagepy.org
Project-URL: Source, https://github.com/caveljan/languagepy/
Project-URL: Tracker, https://github.com/caveljan/languagepy/issues
Keywords: python native language
Platform: UNKNOWN
Classifier: Development Status :: 1 - Planning
Classifier: Environment :: Console
Classifier: Intended Audience :: Developers
Classifier: License :: OSI Approved :: MIT License
Classifier: Programming Language :: Python :: 3.6
Classifier: Topic :: Software Development :: Build Tools
Classifier: Topic :: Text Processing :: Linguistic
Requires-Python: >=3
